README.md
setup.cfg
setup.py
aa_pubsub.egg-info/PKG-INFO
aa_pubsub.egg-info/SOURCES.txt
aa_pubsub.egg-info/dependency_links.txt
aa_pubsub.egg-info/entry_points.txt
aa_pubsub.egg-info/not-zip-safe
aa_pubsub.egg-info/requires.txt
aa_pubsub.egg-info/top_level.txt
pubsub/__init__.py
pubsub/camera.py
pubsub/configs.py
pubsub/publisher.py
pubsub/subscriber.py
pubsub/version.py
testcases/__init__.py
testcases/run_camerasub.py
testcases/run_listener.py
testcases/run_pub.py
testcases/run_switch.py
testcases/run_target_change.py
testcases/test_configs.py